api_connectors/__init__.py
api_connectors/integrations/__init__.py
api_connectors/integrations/appmetrica.py
api_connectors/integrations/dcm.py
api_connectors/integrations/google_analytics.py
api_connectors/integrations/google_base.py
api_connectors/templates/__init__.py
api_connectors/templates/base.py
api_connectors-3.1.dist-info/LICENSE
api_connectors-3.1.dist-info/METADATA
api_connectors-3.1.dist-info/WHEEL
api_connectors-3.1.dist-info/top_level.txt
api_connectors-3.1.dist-info/RECORD
