Metadata-Version: 2.1
Name: api-connectors
Version: 3.1
Summary: A small example package
Home-page: https://github.com/Newander/api_connectors
Author: Newander
Author-email: dasparadeis@gmail.com
License: UNKNOWN
Platform: UNKNOWN
Classifier: Programming Language :: Python :: 3
Classifier: License :: OSI Approved :: MIT License
Classifier: Operating System :: OS Independent
Requires-Python: >=3.6
Requires-Dist: furl (==2.1.0)
Requires-Dist: requests (==2.25.1)
Requires-Dist: oauth2client (==4.1.3)
Requires-Dist: google-api-python-client-py3 (==1.2)
